{
    "name": "Tropical ulcer",
    "qid": "Q6519208",
    "icd_10": "L98.4",
    "description": "medical condition",
    "aliases": [],
    "image": "http://commons.wikimedia.org/wiki/Special:FilePath/Tropical%20ulcer.jpg",
    "url": "https://en.wikipedia.org/wiki/Tropical_ulcer",
    "details": {
        "Medical specialty": [
            {
                "name": "dermatology",
                "qid": "Q171171",
                "url": "https://en.wikipedia.org/wiki/Dermatology"
            }
        ],
        "Subclass of": [
            {
                "name": "ulcer of lower limbs",
                "qid": "Q18557964"
            }
        ]
    }
}